octologo/__init__.py
octologo/__main__.py
octologo/app.tcss
octologo/utils.py
octologo/colors/adi1090x.toml
octologo/colors/cherry.toml
octologo/colors/midnight_abyss.toml
octologo/fonts/Iosevka-Nerd-Font-Complete.ttf
octologo/fonts/JetBrains-Mono-Nerd-Font-Complete.ttf
octologo/styles/first_letter_underlined.py
octologo/styles/underline_core.py
octologo-3.1.0.dist-info/entry_points.txt
octologo-3.1.0.dist-info/LICENSE
octologo-3.1.0.dist-info/WHEEL
octologo-3.1.0.dist-info/METADATA
octologo-3.1.0.dist-info/RECORD
