Metadata-Version: 2.1
Name: octologo
Version: 3.1.0
Summary: Simple program that generates a logo for your open source projects.
Author-email: Leopold Koprivnik <skwal@etik.com>
Requires-Python: >=3.9
Classifier: License :: OSI Approved :: GNU General Public License v3 or later (GPLv3+)
Requires-Dist: pillow>=10.2.0
Requires-Dist: inquirer>=3.2.4
Requires-Dist: toml>=0.10.2
Requires-Dist: textual>=0.38.1
Requires-Dist: click-extra>=4.7.2
Requires-Dist: loguru>=0.7.2
Requires-Dist: textual-wizard>=0.4.3
Project-URL: Home, https://github.com/SkwalExe/octo-logo
